odoo8_addon_account_invoice_accrual-8.0.1.0.0.99.dev28-py3.8-nspkg.pth
odoo_addons/account_invoice_accrual/README.rst
odoo_addons/account_invoice_accrual/__init__.py
odoo_addons/account_invoice_accrual/__openerp__.py
odoo_addons/account_invoice_accrual/account_invoice.py
odoo_addons/account_invoice_accrual/account_invoice_view.xml
odoo_addons/account_invoice_accrual/company.py
odoo_addons/account_invoice_accrual/company_view.xml
odoo_addons/account_invoice_accrual/i18n/account_invoice_accrual.pot
odoo_addons/account_invoice_accrual/i18n/am.po
odoo_addons/account_invoice_accrual/i18n/ar.po
odoo_addons/account_invoice_accrual/i18n/bg.po
odoo_addons/account_invoice_accrual/i18n/bs.po
odoo_addons/account_invoice_accrual/i18n/ca.po
odoo_addons/account_invoice_accrual/i18n/ca_ES.po
odoo_addons/account_invoice_accrual/i18n/cs.po
odoo_addons/account_invoice_accrual/i18n/da.po
odoo_addons/account_invoice_accrual/i18n/de.po
odoo_addons/account_invoice_accrual/i18n/el_GR.po
odoo_addons/account_invoice_accrual/i18n/en_AU.po
odoo_addons/account_invoice_accrual/i18n/en_GB.po
odoo_addons/account_invoice_accrual/i18n/es.po
odoo_addons/account_invoice_accrual/i18n/es_AR.po
odoo_addons/account_invoice_accrual/i18n/es_CL.po
odoo_addons/account_invoice_accrual/i18n/es_CO.po
odoo_addons/account_invoice_accrual/i18n/es_CR.po
odoo_addons/account_invoice_accrual/i18n/es_DO.po
odoo_addons/account_invoice_accrual/i18n/es_EC.po
odoo_addons/account_invoice_accrual/i18n/es_ES.po
odoo_addons/account_invoice_accrual/i18n/es_MX.po
odoo_addons/account_invoice_accrual/i18n/es_PE.po
odoo_addons/account_invoice_accrual/i18n/es_PY.po
odoo_addons/account_invoice_accrual/i18n/es_VE.po
odoo_addons/account_invoice_accrual/i18n/et.po
odoo_addons/account_invoice_accrual/i18n/eu.po
odoo_addons/account_invoice_accrual/i18n/fa.po
odoo_addons/account_invoice_accrual/i18n/fi.po
odoo_addons/account_invoice_accrual/i18n/fr.po
odoo_addons/account_invoice_accrual/i18n/fr_CA.po
odoo8_addon_account_invoice_accrual-8.0.1.0.0.99.dev28.dist-info/METADATA
odoo8_addon_account_invoice_accrual-8.0.1.0.0.99.dev28.dist-info/WHEEL
odoo8_addon_account_invoice_accrual-8.0.1.0.0.99.dev28.dist-info/namespace_packages.txt
odoo8_addon_account_invoice_accrual-8.0.1.0.0.99.dev28.dist-info/top_level.txt
odoo8_addon_account_invoice_accrual-8.0.1.0.0.99.dev28.dist-info/RECORD
